<?xml version="1.0" encoding="UTF-8"?>
<record_update table="sp_instance">
    <sp_instance action="INSERT_OR_UPDATE">
        <active>true</active>
        <class_name/>
        <color>default</color>
        <css/>
        <glyph/>
        <id/>
        <order>0</order>
        <short_description/>
        <size>md</size>
        <sp_column display_value="2">026961b54f013200a68d30318110c795</sp_column>
        <sp_widget display_value="Typeahead Search">fa20ec02cb31020000f8d856634c9ce9</sp_widget>
        <sys_class_name>sp_instance</sys_class_name>
        <sys_created_by>admin</sys_created_by>
        <sys_created_on>2017-02-20 17:15:23</sys_created_on>
        <sys_customer_update>true</sys_customer_update>
        <sys_id>0a6961b54f013200a68d30318110c796</sys_id>
        <sys_mod_count>1</sys_mod_count>
        <sys_name/>
        <sys_package display_value="Service Portal" source="x_76538_service_po">93198fae4f303200a68d30318110c70d</sys_package>
        <sys_policy/>
        <sys_replace_on_upgrade>false</sys_replace_on_upgrade>
        <sys_scope display_value="Service Portal">93198fae4f303200a68d30318110c70d</sys_scope>
        <sys_update_name>sp_instance_0a6961b54f013200a68d30318110c796</sys_update_name>
        <sys_updated_by>admin</sys_updated_by>
        <sys_updated_on>2017-02-20 17:34:36</sys_updated_on>
        <title/>
        <url/>
        <widget_parameters/>
    </sp_instance>
    <sys_translated_text action="delete_multiple" query="documentkey=0a6961b54f013200a68d30318110c796"/>
</record_update>
